aitrans/__init__.py
aitrans/translator.py
aitrans-1.2.3.1.dist-info/LICENSE
aitrans-1.2.3.1.dist-info/METADATA
aitrans-1.2.3.1.dist-info/WHEEL
aitrans-1.2.3.1.dist-info/top_level.txt
aitrans-1.2.3.1.dist-info/RECORD
