Metadata-Version: 2.2
Name: aitrans
Version: 1.2.3.1
Summary: A powerful AI-driven translation library
Home-page: https://github.com/kilolonion/AITranslator.git
Author: kilol
Author-email: kilol <a15607467772@163.com>
License: MIT License
Project-URL: Homepage, https://github.com/kilolonion/AITranslator
Project-URL: Repository, https://github.com/kilolonion/AITranslator.git
Keywords: translation,ai,nlp,language,deep learning
Classifier: Development Status :: 3 - Alpha
Classifier: Intended Audience :: Developers
Classifier: License :: OSI Approved :: MIT License
Classifier: Operating System :: OS Independent
Classifier: Programming Language :: Python :: 3
Classifier: Programming Language :: Python :: 3.7
Classifier: Programming Language :: Python :: 3.8
Classifier: Programming Language :: Python :: 3.9
Classifier: Programming Language :: Python :: 3.10
Classifier: Programming Language :: Python :: 3.11
Requires-Python: >=3.7
License-File: LICENSE
Requires-Dist: openai>=1.0.0
Requires-Dist: aiohttp>=3.8.0
Requires-Dist: httpx>=0.24.0
Requires-Dist: python-dotenv>=0.19.0
Requires-Dist: tenacity>=8.0.0
Requires-Dist: langdetect>=1.0.9
Dynamic: author
Dynamic: home-page
Dynamic: requires-python
